casl/__init__.py
casl/ability.py
PyCASL-1.0.1.dist-info/METADATA
PyCASL-1.0.1.dist-info/WHEEL
PyCASL-1.0.1.dist-info/top_level.txt
PyCASL-1.0.1.dist-info/RECORD
