Metadata-Version: 2.1
Name: PyCASL
Version: 1.0.1
Summary: Pythonized CASL library, see https://casl.js.org
Home-page: https://github.com/hilfestellung/PyCASL
Author: Christian Dein
Author-email: christian.dein@dein-hosting.de
License: LGPL-3.0-or-later 
Platform: UNKNOWN
Classifier: License :: OSI Approved :: GNU Lesser General Public License v3 or later (LGPLv3+)
Classifier: Programming Language :: Python :: 3
Classifier: Programming Language :: Python :: 3.9
